{
    "data": [
        {
            "_id": 11732,
            "username": "Aiden.Becker97",
            "active": true,
            "firstname": "Cordelia",
            "lastname": "Fritsch",
            "cellphone": 1234567899,
            "avatar": "https://s3.amazonaws.com/uifaces/faces/twitter/curiousonaut/128.jpg",
            "createdAt": "23/1/2020"
        },
        {
            "_id": 1689,
            "username": "Marlee_Johnston55",
            "active": false,
            "firstname": "Kailey",
            "lastname": "Cremin",
            "cellphone": 1234567890,
            "avatar": "https://s3.amazonaws.com/uifaces/faces/twitter/rangafangs/128.jpg",
            "createdAt": "5/3/2020"
        },
        {
            "_id": 2481,
            "username": "Jewel_Nienow62",
            "active": false,
            "firstname": "Josianne",
            "lastname": "Mante",
            "cellphone": 1234567890,
            "avatar": "https://s3.amazonaws.com/uifaces/faces/twitter/jimmuirhead/128.jpg",
            "createdAt": "10/5/2020"
        },
        {
            "_id": 97707,
            "username": "Deron_Schmidt69",
            "active": false,
            "firstname": "Dolly",
            "lastname": "Mante",
            "cellphone": 1234567890,
            "avatar": "https://s3.amazonaws.com/uifaces/faces/twitter/antongenkin/128.jpg",
            "createdAt": "13/1/2020"
        },
        {
            "_id": 46856,
            "username": "Kyra.Bins27",
            "active": true,
            "firstname": "Caleb",
            "lastname": "Rice",
            "cellphone": 1234567890,
            "avatar": "https://s3.amazonaws.com/uifaces/faces/twitter/kaspernordkvist/128.jpg",
            "createdAt": "15/6/2020"
        },
        {
            "_id": 71554,
            "username": "Scottie69",
            "active": true,
            "firstname": "Rubie",
            "lastname": "Gorczany",
            "cellphone": 1234567890,
            "avatar": "https://s3.amazonaws.com/uifaces/faces/twitter/anjhero/128.jpg",
            "createdAt": "9/2/2020"
        },
        {
            "_id": 36133,
            "username": "Julianne.Kuphal",
            "active": false,
            "firstname": "Hilbert",
            "lastname": "Pacocha",
            "cellphone": 1234567890,
            "avatar": "https://s3.amazonaws.com/uifaces/faces/twitter/petar_prog/128.jpg",
            "createdAt": "29/5/2020"
        },
        {
            "_id": 49423,
            "username": "Joe4",
            "active": false,
            "firstname": "Camren",
            "lastname": "Schaden",
            "cellphone": 1234567890,
            "avatar": "https://s3.amazonaws.com/uifaces/faces/twitter/VinThomas/128.jpg",
            "createdAt": "12/6/2020"
        },
        {
            "_id": 62779,
            "username": "Cecile_Murphy",
            "active": false,
            "firstname": "Cicero",
            "lastname": "Stehr",
            "cellphone": 1234567890,
            "avatar": "https://s3.amazonaws.com/uifaces/faces/twitter/cbracco/128.jpg",
            "createdAt": "8/5/2020"
        },
        {
            "_id": 6441,
            "username": "Gilberto_Schneider0",
            "active": true,
            "firstname": "Garth0",
            "lastname": "Beer0",
            "cellphone": 1234567890,
            "avatar": "https://s3.amazonaws.com/uifaces/faces/twitter/harry_sistalam/128.jpg",
            "createdAt": "18/1/2020"
        }
    ]
}